meshcut.py
meshcut-0.3.0.dist-info/LICENSE
meshcut-0.3.0.dist-info/METADATA
meshcut-0.3.0.dist-info/WHEEL
meshcut-0.3.0.dist-info/top_level.txt
meshcut-0.3.0.dist-info/RECORD
