Metadata-Version: 2.1
Name: meshcut
Version: 0.3.0
Summary: Utilities to slice 3D triangular meshes.
Home-page: https://github.com/julienr/meshcut
Author: Julien Rebetez
Author-email: julien@fhtagn.net
License: UNKNOWN
Download-URL: https://github.com/julienr/meshcut/tarball/0.1
Keywords: mesh,slice,cross-section,3D,triangular
Platform: UNKNOWN
License-File: LICENSE
Requires-Dist: numpy-stl
Requires-Dist: scipy
Requires-Dist: numpy
